{
  "울산광역시": {
    "년도": 2023,
    "정책수행": {
      "일자리": {
        "세부사업": [
          {
            "사업명": "울산청년 구직지원금",
            "주요내용": "■(대상) 기준 중위소득 120~150% 이하 가구\n■(내용) 최대 180만원 지원",
            "예산": 232
          },
          {
            "사업명": "지방공기업 청년의무고용제",
            "주요내용": "■(대상) 미취업 청년\n■(내용) 일반정규직 정원 100분의 3 고용",
            "예산": 205
          },
          {
            "사업명": "청년 일자리 지원사업",
            "주요내용": "■(대상) 미취업 청년\n■(내용) 청년 채용 인건비 최대 160만원 6개월 지원",
            "예산": 1624
          },
          {
            "사업명": "청년유망직종 채용연계형 인턴 지원사업",
            "주요내용": "■(대상) 직업계고 및 대학생 100명\n■(내용) 인턴십(일 8시간 4개월)",
            "예산": 326
          },
          {
            "사업명": "울산청년일자리센터 운영",
            "주요내용": "■(대상) 청년 일자리센터 운영\n■(내용) 일자리 상담·발굴, 청년일자리 사업 등",
            "예산": 170
          },
          {
            "사업명": "울산청년 일자리희망 온에어",
            "주요내용": "■(대상) 취업준비 청년 등\n■(내용) 진로상담 멘토링 토크 등",
            "예산": 110
          },
          {
            "사업명": "울산청년 희망공제 사업",
            "주요내용": "■(대상) 제조업 중소기업에 2년 이상 재직 중 미혼 청년\n■(내용) 50만원(시20, 근로자30) 지원",
            "예산": 262
          },
          {
            "사업명": "청년채용 장려금 추가지원 사업",
            "주요내용": "■(대상) 사업주\n■(내용) 고용부 장려금 결정 금액의 10% 추가지원",
            "예산": 2700
          },
          {
            "사업명": "울산청년 취업역량강화 패키지 사업",
            "주요내용": "■(대상) 미취업청년 50명\n■(내용) 취업 연계 맞춤형 역량 강화 패키지 지원",
            "예산": 20
          },
          {
            "사업명": "행정체험형 청년인턴 채용사업",
            "주요내용": "■(대상) 미취업 청년 20명\n■(내용) 시 본청 등 체험형 인턴 근무",
            "예산": 324
          },
          {
            "사업명": "시 공공기관 청년인턴 채용사업",
            "주요내용": "■(대상) 울산거주 만15세~34세 미취업청년 80명\n■(내용) 울산연구원 등 11개 기관 체험형 인턴",
            "예산": 843
          },
          {
            "사업명": "대학생 아르바이트 채용사업",
            "주요내용": "■(대상) 관내 대학생 150명\n■(내용) 진로탐색 및 행정업무 체험기회 제공",
            "예산": 330
          },
          {
            "사업명": "문화예술교육사 인턴십 지원",
            "주요내용": "■(대상) 문화예술교육사 자격증 취득자\n■(내용) 인턴십 지원, 기관별 특화 프로그램 운영",
            "예산": 168
          },
          {
            "사업명": "청년CEO 육성사업",
            "주요내용": "■(대상) 만18세~39세 청년, 예비~1년미만 창업자\n■(내용) 창업공간, 교육·컨설팅 등 지원",
            "예산": 1200
          },
          {
            "사업명": "지식기술 청년창업 지원",
            "주요내용": "■(대상) 지식기술분야 청년 (예비)창업자 20개사\n■(내용) 창업공간, 교육·컨설팅 등 지원",
            "예산": 300
          },
          {
            "사업명": "톡톡팩토리 운영",
            "주요내용": "■(대상) 만18세~39세 청년, 예비~7년미만 창업자\n■(내용) 제조설비, 공간지원",
            "예산": 650
          },
          {
            "사업명": "울산관광기업지원센터 운영",
            "주요내용": "■(대상) 7년미만 (예비)사업자 등\n■(내용) 관광분야 사업자 및 전문가 양성 및 일자리 지원",
            "예산": 2000
          },
          {
            "사업명": "청년농업인 영농정착금 지원",
            "주요내용": "■(대상) 만18세이상~40세미만, 영농경력 3년이하 독립경영자\n■(내용) 연차별 정착금 3년간 매월 지원(110~90만원)",
            "예산": 340
          },
          {
            "사업명": "청년농업인 경쟁력 제고사업",
            "주요내용": "■(대상) 만40세 미만 청년농업인\n■(내용) 청년농업인 맞춤형 경영 기술지원 체계 구축",
            "예산": 150
          },
          {
            "사업명": "청년농업인 경영 진단분석 컨설팅 사업",
            "주요내용": "■(대상) 농식품부 영농정착 지원사업 대상자 및 청년농업인\n■(내용) 경영상태 진단분석 후 컨설팅 서비스 제공",
            "예산": 6
          }
        ],
        "사업수": 20,
        "총예산": 11960
      },
      "주거": {
        "세부사업": [
          {
            "사업명": "상안지구 행복주택 건립",
            "주요내용": "■(대상) 청년·신혼부부\n■(내용) 102호 공급",
            "예산": 1913
          },
          {
            "사업명": "(구)울주군청사 복합개발사업",
            "주요내용": "■(대상) 청년·신혼부부\n■(내용) 160호 공급",
            "예산": 5023
          },
          {
            "사업명": "희망상가 품은 청년희망주택 건립",
            "주요내용": "■(대상) 청년세대\n■(내용) 36호 공급",
            "예산": 3275
          },
          {
            "사업명": "신정동 청년희망주택 건립사업",
            "주요내용": "■(대상) 청년세대\n■(내용) 38호 공급",
            "예산": 745
          },
          {
            "사업명": "태화동 청년희망주택 건립사업",
            "주요내용": "■(대상) 청년세대\n■(내용) 16호 공급",
            "예산": 170
          },
          {
            "사업명": "매곡산업단지 복합개발사업",
            "주요내용": "■(대상) 청년·신혼부부\n■(내용) 144호 공급",
            "예산": 14984
          },
          {
            "사업명": "청년 주거급여 분리지급",
            "주요내용": "■(대상) 미혼청년 180가구\n■(내용) 청년 주거급여 분리 지급",
            "예산": 500
          },
          {
            "사업명": "신혼부부 가구 주거비 지원",
            "주요내용": "■(대상) 공공임대주택 입주 신혼부부\n■(내용) 주거비 지원",
            "예산": 2400
          },
          {
            "사업명": "청년가구 주거비 지원",
            "주요내용": "■(대상) 청년세대 500가구\n■(내용) 임차료 및 임차보증금 이자 지원",
            "예산": 1000
          },
          {
            "사업명": "청년월세 한시 특별 지원사업",
            "주요내용": "■(대상) 청년세대 1,600가구\n■(내용) 임대료 월 20만원 지원",
            "예산": 2066
          },
          {
            "사업명": "청년 주택임차보증금 이자 지원(일몰사업)",
            "주요내용": "■(대상) 만19세~34세 무주택 청년\n■(내용) 임차보증금 1억5천 이하 주택 대상 5천만원 한도 3% 이내 이자지원",
            "예산": 180
          }
        ],
        "사업수": 11,
        "총예산": 32256
      },
      "교육": {
        "세부사업": [
          {
            "사업명": "울산인재평생교육진흥원 우수인재 장학사업",
            "주요내용": "■(대상) 초중고등학교, 대학생\n■(내용) 울산사랑, 울산인재, 드림, 희망 등",
            "예산": 980
          },
          {
            "사업명": "대학생 학자금 대출 이자 지원",
            "주요내용": "■(대상) 울산 대학교 재(휴)학생\n■(내용) '17년 이후 한국장학 재단 신규대출금 '21년 발생이자 지원",
            "예산": 46
          },
          {
            "사업명": "울산과학기술원 지역인재전형",
            "주요내용": "■(대상) 지역인재전형 65명 선발\n■(내용) 학사운영비 지원",
            "예산": 2752
          },
          {
            "사업명": "AI배울랑교",
            "주요내용": "■(대상) 재직자, 대학생 등\n■(내용) AI·블록체인 전문 인력 양성",
            "예산": 2094
          },
          {
            "사업명": "인공지능대학원 지원사업",
            "주요내용": "■(대상) 석박사급 학생\n■(내용) AI 인재 혁신프로그램 개발 등",
            "예산": 3898
          },
          {
            "사업명": "지자체-대학 협력기반 지역혁신사업",
            "주요내용": "■(대상) 울산·경남 대학생\n■(내용) 공유대학 구축 및 운영, 산학협력 지원",
            "예산": 23058
          },
          {
            "사업명": "울산 콘텐츠코리아랩 운영",
            "주요내용": "■(대상) 콘텐츠 창작자, 예비 창업자 등\n■(내용) 시설·장비 무상사용, 콘텐츠 교육 등",
            "예산": 1380
          },
          {
            "사업명": "울산 마이스 인재양성",
            "주요내용": "■(대상) 대학생, 취업 준비생\n■(내용) 마이스 분야 교육 프로그램 운영",
            "예산": 14
          },
          {
            "사업명": "산학일체형 도제학교 지원사업",
            "주요내용": "■(대상) 80명(울산공업고등학교 자동화기계과)\n■(내용) 일학습병행제 교육",
            "예산": 150
          },
          {
            "사업명": "직업교육혁신지구 지원사업",
            "주요내용": "■(대상) 직업계고 2, 3학년 재학생\n■(내용) 일자리 교육 기반 조성 및 취업 지원",
            "예산": 1000
          },
          {
            "사업명": "대학일자리센터 운영",
            "주요내용": "■(대상) 울산대학교, 울산과학대학교\n■(내용) 진로지도, 직업훈련 등",
            "예산": 400
          },
          {
            "사업명": "대학생 중소기업 인턴십 지원",
            "주요내용": "■(대상) 수출중소기업 중 대학생 인턴 희망업체·대학생\n■(내용) 인턴 활동비 300만원",
            "예산": 60
          },
          {
            "사업명": "국제개발협력 글로벌 청년인재 육성(U-FLY)",
            "주요내용": "■(대상) 울산 청년 8명\n■(내용) 국제개발협력 및 공적 개발원조 사업 실무경험 기회 제공",
            "예산": 163
          }
        ],
        "사업수": 13,
        "총예산": 35995
      },
      "복지·문화": {
        "세부사업": [
          {
            "사업명": "청년희망키움통장 지원사업 (일몰사업)",
            "주요내용": "■(대상) 근로·사업소득 있는 생계급여 수급청년\n■(내용) 근로소득 공제액(10만원)+근로소득장려금(31만원) 적립",
            "예산": 45
          },
          {
            "사업명": "청년저축계좌 지원사업 (일몰사업)",
            "주요내용": "■(대상) 근로·사업소득 있는 차상위계층 청년\n■(내용) 본인저축액(10만원)에 따른 근로소득 장려금 30만원 적립",
            "예산": 425
          },
          {
            "사업명": "청년내일저축계좌 지원사업",
            "주요내용": "■(대상) 근로·사업소득 있는 청년\n■(내용) 본인저축액(10만원)에 따른 정부지원금 적립",
            "예산": 3214
          },
          {
            "사업명": "니트청년 지원",
            "주요내용": "■(대상) 만19세~34세 니트청년 100명\n■(내용) 니트청년 발굴 및 지원 프로그램 운영",
            "예산": 100
          },
          {
            "사업명": "청년사회서비스사업단 운영",
            "주요내용": "■(대상) 울산지역 청년\n■(내용) 사회서비스제공",
            "예산": 129
          },
          {
            "사업명": "청년마음건강센터 운영",
            "주요내용": "■(대상) 정신질환자 및 정신증 고위험군 청(소)년\n■(내용) 정신건강교육 치료비 지원 등",
            "예산": 50
          },
          {
            "사업명": "청년중독관리사업 추진",
            "주요내용": "■(대상) 도박중독 청년\n■(내용) 중독선별검사, 재활 프로그램 운영 등",
            "예산": 100
          },
          {
            "사업명": "보호종료아동 자립수당",
            "주요내용": "■(대상) 시설퇴소 및 가정 위탁보호종결 등 만18세 이후 보호종료 아동\n■(내용) 매월 35만원 지원",
            "예산": 512
          },
          {
            "사업명": "청소년쉼터 퇴소청소년 자립지원 수당",
            "주요내용": "■(대상) 청소년쉼터 퇴소 18세 이상 ■(내용) 월 30만원 (퇴소 후 30년 이내)",
            "예산": 41
          },
          {
            "사업명": "청소년한부모 자립지원",
            "주요내용": "■(대상) 중위소득 60%이하 만18세 미만 자녀 양육 한부모\n■(내용) 청소년한부모 아동양육비(월35만원), 자립촉진수당(월10만원) 지원",
            "예산": 120
          },
          {
            "사업명": "울산글로벌게임센터 운영",
            "주요내용": "■(대상) 게임기업, 게임분야 진로 청년 등\n■(내용) 장비 및 시설 운영, 인력양성 등",
            "예산": 2400
          },
          {
            "사업명": "울산웹툰캠퍼스 운영",
            "주요내용": "■(대상) 웹툰산업 분야 진로 청년 등\n■(내용) 작가입주실 운영, 인력양성 등",
            "예산": 200
          },
          {
            "사업명": "울산청년 예술지원",
            "주요내용": "■(대상) 만19세이상 39세이하 관내 청년예술인\n■(내용) 창작발표 활동 직접 경비 지원",
            "예산": 120
          },
          {
            "사업명": "울산 비보이 페스티벌",
            "주요내용": "■(대상) 비보이 댄서 등\n■(내용) 비보이 배틀 경연",
            "예산": 120
          },
          {
            "사업명": "거리공연 지원",
            "주요내용": "■(대상) 거리공연 가능 공연 분야 예술가\n■(내용) 공연 기회 제공, 출연료 지급 등",
            "예산": 50
          },
          {
            "사업명": "울산 스트릿댄스 페스티벌",
            "주요내용": "■(대상) 비보이·스트리트 댄서 등\n■(내용) 스트리트 댄싱 대회",
            "예산": 100
          }
        ],
        "사업수": 16,
        "총예산": 7726
      },
      "참여·권리": {
        "세부사업": [
          {
            "사업명": "울산청년정책조정위원회 운영",
            "주요내용": "■(위원) 20명\n■(내용) 청년정책 주요사항 심의",
            "예산": 8
          },
          {
            "사업명": "시 위원회 청년위원 참여 제고",
            "주요내용": "■(대상) 시 소관 위원회(199개)\n■(내용) 청년위원 위촉율 확대",
            "예산": 0
          },
          {
            "사업명": "울산청년정책네트워크 운영",
            "주요내용": "■(대상) 50명\n■(내용) 청년정책 제안 정책협의 등",
            "예산": 54
          },
          {
            "사업명": "청년주간 운영",
            "주요내용": "■(대상) 3,000명\n■(내용) 청년 참여확대 소통 협업",
            "예산": 90
          },
          {
            "사업명": "지역사회 공감확산 시리즈 캠페인 사업",
            "주요내용": "■(대상) 청년미래 응원\n■(내용) 영상제작(2편)",
            "예산": 73
          },
          {
            "사업명": "청년거점공간 운영",
            "주요내용": "■(대상) 관내 청년\n■(내용) 소통·휴게공간·회의실 등 역량개발 공간 조성",
            "예산": 102
          },
          {
            "사업명": "청년거점공간 설치지원 사업",
            "주요내용": "■(대상) 동구, 북구\n■(내용) 지역 내 권역별 청년공간 설치지원",
            "예산": 100
          },
          {
            "사업명": "청년정책 정보플랫폼 활성화",
            "주요내용": "■(목적) 청년정책 정보 접근성 제고\n■(내용) 응용 소프트웨어, 통합관리 시스템 구축 등",
            "예산": 15
          },
          {
            "사업명": "청년정책 홍보서포터즈 운영",
            "주요내용": "■(대상) 관내 청년 15명\n■(내용) 청년정책 홍보 지원",
            "예산": 10
          },
          {
            "사업명": "청년센터 서포터즈 운영",
            "주요내용": "■(대상) 관내 청년 10명\n■(내용) 청년센터 콘텐츠 홍보 등",
            "예산": 15
          },
          {
            "사업명": "청년공동체 활성화 사업",
            "주요내용": "■(대상) 청년공동체 (5인 이상 6개팀)\n■(내용) 청년공동체 발굴, 활동비 지원 등",
            "예산": 60
          },
          {
            "사업명": "청년센터 행사운영",
            "주요내용": "■(대상) 관내 청년\n■(내용) 청년 지원을 위한 교육·상담·교류회 등 진행",
            "예산": 75
          },
          {
            "사업명": "청년활동 경험 지원사업",
            "주요내용": "■(대상) 관내 청년단체(10개팀)\n■(내용) 청년커뮤니티 활성화 등",
            "예산": 60
          }
        ],
        "사업수": 13,
        "총예산": 662
      }
    }
  },
  "울산광역시 중구": {
    "년도": 2023,
    "정책수행": {
      "일자리": {
        "세부사업": [
          {
            "사업명": "청년 면접정장 대여사업 운영",
            "주요내용": "■ 지원대상 : 중구거주 19세~34세이하 청년\n■ 지원기준 : 청년구직자\n■ 지원내용 : 재킷, 바지, 치마, 셔츠, 블라우스, 넥타이 등",
            "예산": 30
          },
          {
            "사업명": "맞춤형 청년 취업역량강화 프로그램 운영",
            "주요내용": "■ 지원대상 : 19세~34세이하\n■ 지원기준 : 청년구직자\n■ 지원내용 : 자기소개서·면접 특강, 이미지메이킹, 모의면접 등 운영 ※ 2023년 사업은 공공기관 및 일반기업 인사담당자를 멘토로 선정하여 공공기관 회의실 및 중구 대회의실에서 멘토링데이로 운영 예정",
            "예산": 10
          },
          {
            "사업명": "청년디딤터 운영",
            "주요내용": "■ 지원대상 : 청년창업기업 지원 및 청년협력공간 제공\n■ 지원기준 : 청년창업가(39세이하), 중구거주 19세~34세이하 청년\n■ 지원내용 : 창업공간 지원, 창업지원프로그램 운영 등, 지역청년 교류 지원, 청년 협력공간 제공 등",
            "예산": 120
          },
          {
            "사업명": "대학생 행정체험 프로그램",
            "주요내용": "■ 지원대상 : 본인 또는 부모가 1년이상 중구에 주민등록 되어있는 대학생\n■ 지원기준 : 휴학생, 예비대학생, 사이버대학, 대학원생 및 기참여자는 제외\n■ 지원내용 : 대학생에게 행정보조 및 현장근무 등 다양한 구정업무 체험을 통해 일 경험 및 학비마련 기회 제공",
            "예산": 66
          },
          {
            "사업명": "청년 특성 야시장 운영",
            "주요내용": "■ 지원대상 : 중구 원도심내 전통시장 및 상점가 야시장 창업 청년\n■ 지원내용 : 청년 특성 야시장 부스 보수(38대), 홍보물 제작, 배포와 버스킹 등 문화공연 프로그램 운영으로 방문객을 유입하여 매출을 증대, 원도심 상권 활성화",
            "예산": 100
          }
        ],
        "사업수": 5,
        "총예산": 326
      },
      "복지·문화": {
        "세부사업": [
          {
            "사업명": "청년예술제",
            "주요내용": "■ 지원대상 : 지역 청년 및 청년예술가\n■ 지원내용 : 거리공연(버스킹), 청년작가 작품전시, 청년정책 세미나, 토크콘서트 등",
            "예산": 25
          }
        ],
        "사업수": 1,
        "총예산": 25
      },
      "주거": {
        "세부사업": [
          {
            "사업명": "신혼부부 주택 전세자금 대출이자 지원",
            "주요내용": "■ 지원대상 : 신혼가구 200가구\n■ 지원기준 : 혼인신고일 5년이내, 기준 중위소득 180% 이하이면서 무주택 신혼부부, 공고일 이전 금융기관으로 1억5000만원 이하의 주택전세자금 대출을 받은자, 신청일 현재 부부가 중구 관내 동일 주소에 등재되어 거주하는 신혼부부\n■ 지원내용 : 무주택 신혼부부 주택 전세자금 대출이자 지원(대출잔액의 1.5%에 해당하는 이자 연1회 최대 100만원, 최대 2년 지원)",
            "예산": 50
          },
          {
            "사업명": "청년 주거상담소 지정 운영",
            "주요내용": "■ 지원대상 : 18세~34세 청년가구\n■ 지원기준 : 보증금 7,000만원 이하(보증금 2,000만원·월세 50만원)의 임대차 거래 청년\n■ 지원내용 : 청년이 보증금 7,000만원 이하(보증금 2,000만원·월세 50만원)의 주택임대차 계약시 청년에게 경제적 도움을 주기 위한 중개보수 50% 감면(최대 14만원)",
            "예산": 0
          }
        ],
        "사업수": 2,
        "총예산": 50
      },
      "참여·권리": {
        "세부사업": [
          {
            "사업명": "청년정책위원회 운영",
            "주요내용": "■ 지원대상 : 청년정책위원회 위원\n■ 지원내용 : 정기회의 2회 운영",
            "예산": 1
          },
          {
            "사업명": "청년정책협의체 및 운영",
            "주요내용": "■ 지원대상 : 청년정책협의체 위원\n■ 지원내용 : 역량강화 프로그램 운영, 정기회의·분과회의 운영",
            "예산": 16
          }
        ],
        "사업수": 2,
        "총예산": 17
      }
    }
  },
  "울산광역시 남구": {
    "년도": 2023,
    "정책수행": {
      "일자리": {
        "세부사업": [
          {
            "사업명": "스타트업 창의차고 운영",
            "주요내용": "■ 지원대상 : 입주공간 5실\n■ 지원기준 : 청년창업기업\n■ 지원내용 : 창업공간 지원",
            "예산": 45
          },
          {
            "사업명": "청년일자리카페 운영",
            "주요내용": "■ 지원대상 : 19~39세 청년\n■ 지원기준 : 주소 및 생활권이 울산 남구인 청년\n■ 지원내용 : 취업지원 공간대여 및 취업역량강화 프로그램 운영",
            "예산": 262
          },
          {
            "사업명": "대학생 아르바이트 사업",
            "주요내용": "■ 지원대상 : 전문대학 이상 재학생\n■ 지원기준 : 본인 또는 학부모가 남구 주민등록 되어 있는 학생\n■ 지원내용 : 구정관련 행정업무 경험 및 학자금 마련 기회 제공",
            "예산": 163
          },
          {
            "사업명": "청년창업 점포지원 사업",
            "주요내용": "■ 지원대상 : 50명(팀)\n■ 지원기준 : 관내 신규 창업을 목적으로 사업자등록을 취득 하는 만19~39세 청년\n■ 지원내용 : 시설개선비, 임차료",
            "예산": 334
          }
        ],
        "사업수": 4,
        "총예산": 804
      },
      "교육": {
        "세부사업": [
          {
            "사업명": "청년창업 컨설팅 및 교육 프로그램 운영",
            "주요내용": "■ 지원대상 : 창업희망자 30명\n■ 지원내용 : 청년창업가 교육 및 특강을 통한 역량강화",
            "예산": 40
          },
          {
            "사업명": "청년창업 아카데미 운영",
            "주요내용": "■ 지원대상 : 창업희망자 40명\n■ 지원내용 : 창업 기초 및 심화 교육을 통한 창업 역량강화 및 후속지원",
            "예산": 15
          }
        ],
        "사업수": 2,
        "총예산": 55
      },
      "복지·문화": {
        "세부사업": [
          {
            "사업명": "청년의 날 행사",
            "주요내용": "■ 지원대상 : 청년 100명\n■ 지원내용 : 특강, 체험행사 등",
            "예산": 20
          },
          {
            "사업명": "청년창업가 사회환원 사업",
            "주요내용": "■ 지원대상 : 관내 취약계층\n■ 지원내용 : 청년창업가 기부 및 지역인재 우선 채용 등",
            "예산": 10
          },
          {
            "사업명": "남구장학재단 장학생 학자금 지급",
            "주요내용": "■ 지원대상 : 남구장학재단 선발 장학생\n■ 지원기준 : 본인 또는 부모가 남구에 1년 이상 거주\n■ 지원내용 : 장학금 지급",
            "예산": 400
          }
        ],
        "사업수": 3,
        "총예산": 430
      },
      "참여·권리": {
        "세부사업": [
          {
            "사업명": "청년정책협의체 운영",
            "주요내용": "■ 지원대상 : 위원 20명\n■ 지원기준 : 분야별 분과활동\n■ 지원내용 : 회의참석수당, 활동비등",
            "예산": 11
          },
          {
            "사업명": "토요 청년아지트 운영",
            "주요내용": "■ 지원대상 : 19~39세 청년\n■ 지원기준 : 주소 및 생활권이 울산 남구인 청년\n■ 지원내용 : 커뮤니티 공간 제공",
            "예산": 3
          },
          {
            "사업명": "청년기자단 운영",
            "주요내용": "■ 지원대상 : 19~39세 청년\n■ 지원기준 : 남구 거주 또는 활동하는 청년\n■ 지원내용 : 콘텐츠 활동비 등",
            "예산": 6
          },
          {
            "사업명": "청년정책위원회 운영",
            "주요내용": "■ 지원대상 : 위원 20명\n■ 지원기준 : 청년정책 자문 및 심의\n■ 지원내용 : 회의참석수당",
            "예산": 4
          }
        ],
        "사업수": 4,
        "총예산": 24
      }
    }
  },
  "울산광역시 동구": {
    "년도": 2023,
    "정책수행": {
      "일자리": {
        "세부사업": [
          {
            "사업명": "청년창업지원",
            "주요내용": "■ 지원대상: 예비 청년창업자\n■ 지원기준: 만18세이상 39세이하 빈점포 활용 청년창업가\n■ 지원내용: 청년창업가 육성을 위한 창업 교육 및 컨설팅 지원",
            "예산": 10
          }
        ],
        "사업수": 1,
        "총예산": 10
      },
      "참여·권리": {
        "세부사업": [
          {
            "사업명": "청년정책 네트워크 활성화",
            "주요내용": "■ 지원대상: 청년정책협의체\n■ 지원기준: 청년정책협의체 위원\n■ 지원내용: 분과활동 수당 및 역량강화프로그램 운영 등",
            "예산": 19
          }
        ],
        "사업수": 1,
        "총예산": 19
      },
      "복지·문화": {
        "세부사업": [
          {
            "사업명": "청년센터 운영",
            "주요내용": "■ 지원대상: 관내 청년\n■ 지원기준: 만18세이상 39세이하\n■ 지원내용: 동구 청년활동 공간 및 취·창업 연계, 공유 오피스 운영 등 청년정책 통합적 제공",
            "예산": 67
          }
        ],
        "사업수": 1,
        "총예산": 67
      }
    }
  },
  "울산광역시 북구": {
    "년도": 2023,
    "정책수행": {
      "일자리": {
        "세부사업": [
          {
            "사업명": "취업 준비청년 일드림패키지",
            "주요내용": "■ 지원대상 : 만18세~39세 구직자\n■ 지원기준 : 북구 거주\n■ 지원내용 : 면접정장 대여, 취업사진(2만원), 헤어메이크업(5만원), 자격시험 응시료(5만원)",
            "예산": 44
          },
          {
            "사업명": "북구 청년창업지원센터 운영",
            "주요내용": "■ 지원대상 : 만18세~39세 (예비)창업자\n■ 지원기준 : 북구 거주(사업자)\n■ 지원내용 : 창업공간지원 및 액셀러레이팅(입주공간지원 및 멘토링, 교육 등)",
            "예산": 157
          }
        ],
        "사업수": 2,
        "총예산": 201
      },
      "교육": {
        "세부사업": [
          {
            "사업명": "차오름장학금 지급",
            "주요내용": "■ 지원대상 : 1~3학년 1학기 등록대학생\n■ 지원기준 : 북구 거주, 중위소득70%\n■ 지원내용 : 대학등록금 지원",
            "예산": 120
          }
        ],
        "사업수": 1,
        "총예산": 120
      },
      "참여·권리": {
        "세부사업": [
          {
            "사업명": "청년정책협의체 운영",
            "주요내용": "■ 지원대상 : 북구 청년정책협의체\n■ 지원기준 : 만19세~34세\n■ 지원내용 : 회의참석수당 및 실무분과 활동비",
            "예산": 6
          },
          {
            "사업명": "청년정책위원회 운영",
            "주요내용": "■ 역할 : 건전한 청년정책 수립을 위하여 북구에 맞는 청년정책을 수립\n■ 구성 : 청년정책 담당분야별 공무원, 북구의회 의원, 전문위원, 청년 등 총 20명",
            "예산": 1
          },
          {
            "사업명": "청년 소셜 리빙랩 운영",
            "주요내용": "■ 지원대상 : 19세~34세 청년(팀)\n■ 지원기준 : 북구 거주\n■ 지원내용 : 사회문제 발굴·해결에 관한 실험활동비 지원",
            "예산": 12
          },
          {
            "사업명": "청년 면접관 제도 운영",
            "주요내용": "■ 지원대상 : 19세~34세 청년 공무원, 청년정책협의체 위원 등\n■ 지원내용 : 기간제 등 근로자 채용 시, 지원자의 30% 이상이 청년일 경우 청년면접관을 위촉",
            "예산": 0
          }
        ],
        "사업수": 4,
        "총예산": 19
      }
    }
  },
  "울산광역시 울주군": {
    "년도": 2023,
    "정책수행": {
      "일자리": {
        "세부사업": [
          {
            "사업명": "청년창업아카데미 운영",
            "주요내용": "■ 지원대상 : 만18세~39세 이하 청년창업자\n■ 지원기준 : 창업동기, 역량 및 의지, 사업성, 계획성\n■ 지원내용 : - 창업공간 및 집기 제공, 교육·컨설팅, 창업활동비 지원, 창업아이디어 공모전 등 진행",
            "예산": 500
          },
          {
            "사업명": "꿈꾸는 청년대장간 사업",
            "주요내용": "■ 지원대상 : 사업자등록 7년 미만의청년창업기업 또는 직원의 50%이상이 청년층\n■ 지원기준 : 창업의지, 역량, 시장성, 파급효과 등\n■ 지원내용 : 공간지원, 협의체 구성, 마케팅 지원, 멘토링 및 컨설팅 지원, 판로개척 지원, 네트워크 지원, 투자유치 지원",
            "예산": 200
          },
          {
            "사업명": "중소기업 청년인턴사업",
            "주요내용": "■ 지원대상\n- 기업 : 울주군에 사업장을 둔 고용보험 상시근로자수 5인 이상인 중소기업(제조업체)으로써 청년 미취업자(울주군민)을 인턴 및 정규직으로 신규 채용할 의사가 있는 기업\n- 인턴 : 인턴신청일 현재 울주군에 주민등록이 되어있는 만39세 이하의 청년미취업자\n■ 지원내용\n- 기업 : 인턴 1인당 월80만원 최대 9개월간 지원(인턴 3개월 + 정규직 근무 6개월)\n- 인턴 : 정규직 전환시 100만원, 정규직 근무 6개월 후 200만원 지원",
            "예산": 450
          },
          {
            "사업명": "대학생 아르바이트 사업",
            "주요내용": "■ 지원대상 : 본인 또는 부모가 울주군에 주민등록이 되어 있는 대학생\n■ 지원기준 : 공개 추첨을 통한 참여자 선정\n■ 지원내용 : 대학생에게 다양한 군정업무 체험을 통한 일 경험 제공",
            "예산": 164
          },
          {
            "사업명": "청년 꿈 날개 지원 사업(면접정장대여사업)",
            "주요내용": "■ 지원대상 : 울주군에 주민등록을 둔 청년 구직자(만18~39세)\n■ 지원내용 : 면접용 정장(자켓, 바지,스커트) 무료 대여",
            "예산": 24
          }
        ],
        "사업수": 5,
        "총예산": 1338
      },
      "주거": {
        "세부사업": [
          {
            "사업명": "신혼부부 주택 매입·전세자금 대출이자 지원",
            "주요내용": "■ 지원대상\n- 신청일 기준 혼인신고일 1년 이내 또는 3개월 이내 혼인신고 예정인 신혼 부부\n- 울주군 거주지 마련하여 입주 예정 (부부 모두 실거주)인 가구\n- 부부 모두 무주택자, 부부 합산 연소득 1억 이하 가구\n■ 지원내용\n- 신혼부부가구의 주택 매입·전세자금 대출이자 지원(최대2% 한도)\n- 대출금 최대 2억 한도, 이자 최대 400만원/년",
            "예산": 2540
          },
          {
            "사업명": "신혼부부 주거비용 지원사업",
            "주요내용": "■ 지원대상\n- 신청일 기준 혼인신고일이 1년 이내 이면서 부부 모두 울주군 6개월 이상 거주\n- 부부합산 소득기준중위소득 200% 이하인 가구(2인기준)\n■ 지원내용 : 2년간 신혼부부 가구의 소득수준에 따라 월 5~9만원 차등 지원",
            "예산": 126
          }
        ],
        "사업수": 2,
        "총예산": 2666
      },
      "복지·문화": {
        "세부사업": [
          {
            "사업명": "작은 결혼식 지원",
            "주요내용": "■ 지원대상 : 울주군 주소,3개월 이내 혼인신고,예비부부10쌍\n■ 지원내용 : 예식공간 무료대관, 웨딩패키지 지원, 부부부모 교육지원",
            "예산": 32
          }
        ],
        "사업수": 1,
        "총예산": 32
      },
      "참여·권리": {
        "세부사업": [
          {
            "사업명": "청년참여예산제",
            "주요내용": "■ 지원대상 : 청년의 삶 전반\n■ 지원기준 : 만18세~39세\n■ 지원내용 : 청년정책 수립 및 반영",
            "예산": 0
          },
          {
            "사업명": "울주군 청년센터 운영",
            "주요내용": "■ 지원대상 : 울주군 청년전체\n■ 지원기준 : 만18세~39세\n■ 지원내용 : 청년성장지원, 청년정책지원, 청년활동지원, 홍보사업",
            "예산": 510
          },
          {
            "사업명": "청년청책협의체 운영",
            "주요내용": "■ 지원대상 : 울주청정넷\n■ 지원기준 : 분과활동\n■ 지원내용 : 정책발굴 분과회의 활동별 활동비 지급",
            "예산": 190
          }
        ],
        "사업수": 3,
        "총예산": 700
      }
    }
  }
}